datascribe/__init__.py
datascribe/data/ae_data.csv
datascribe/data/ae_processed.csv
datascribe/datasets.py
datascribe/feature_engineering.py
datascribe/metrics.py
datascribe/model.py
datascribe/outputs.py
datascribe/scribe.py
datascribe/summary_stats.py
datascribe/workflow.py
datascribe-1.0.0.dist-info/LICENSE
datascribe-1.0.0.dist-info/METADATA
datascribe-1.0.0.dist-info/WHEEL
datascribe-1.0.0.dist-info/RECORD
