Metadata-Version: 2.1
Name: datascribe
Version: 1.0.0
Summary: Useful tools to help you document and describe data processing and modelling
License: MIT
Author: Chloe Hutton
Author-email: pydatascribe@outlook.com
Requires-Python: >=3.9,<3.13
Classifier: License :: OSI Approved :: MIT License
Classifier: Programming Language :: Python :: 3
Classifier: Programming Language :: Python :: 3.9
Classifier: Programming Language :: Python :: 3.10
Classifier: Programming Language :: Python :: 3.11
Classifier: Programming Language :: Python :: 3.12
Requires-Dist: graphviz (>=0.8.3)
Requires-Dist: matplotlib (>=3.2)
Requires-Dist: natsort (>=6.2,<7.0)
Requires-Dist: numpy (>=1.21,<2.0)
Requires-Dist: pandas (>=2.1.4,<3.0.0)
Requires-Dist: pandoc (>=2.3,<3.0)
Requires-Dist: pypandoc (>=0.8.0,<2.0)
Requires-Dist: scikit-learn (>=1.4.0rc1,<2.0)
Requires-Dist: tabulate (>=0.8,<1.0)
Requires-Dist: unidecode (>=1.3,<2.0)
